{
    "forge_marker": 1,
    "variants": {
		"normal": [ { } ],
		"inventory": [
			{
			   "model": "doomweapon:open_sword.obj"
			}
		]
	},
	"defaults" : {
	   "transform": {
	       "thirdperson_righthand": {
	           "rotation": [ 0, 180, 0 ],
	           "translation": [ -0.50, 0.00, -0.4 ],
	           "scale": [ 1.00, 1.00, 1.00 ]
	       },
	       "thirdperson_lefthand": {
		      "rotation": [ 0, 180, 0 ],
		      "translation": [ 0.50, 0.00, -0.40 ],
	          "scale": [ 1.00, 1.00, 1.00 ]
	       },
	       "firstperson_righthand": {
		      "rotation": [ 0, 190, 0 ],
		      "translation": [ -0.70, -0.10, -0.50 ],
		      "scale": [ 0.90, 0.90, 0.90 ]
	       },
	       "firstperson_lefthand": {
		      "rotation": [ 0, 190, 0 ],
		      "translation": [ 0.40, -0.10, -0.50 ],
		      "scale": [ 0.90, 0.90, 0.90 ]
	       },
	       "gui": {
		      "rotation": [ 96, 50, 216 ],
		      "translation": [ -0.10, -0.70, 0.00 ],
		      "scale": [ 0.70, 0.70, 0.70 ]
	       },
	       "head": {
		      "rotation": [ 0, 0, 0 ],
		      "translation": [ 0.00, 0.00, 0.00 ],
		      "scale": [ 1.00, 1.00, 1.00 ]
	       },
	       "fixed": {
		      "rotation": [ 90, -45, 90 ],
		      "translation": [ 0.50, -1.20, 0.50 ],
		      "scale": [ 1.00, 1.00, 1.00 ]
	       },
	       "ground": {
		      "rotation": [ 0, 0, 0 ],
		      "translation": [ 0.60, 0.20, 0.60 ],
		      "scale": [ 1.00, 1.00, 1.00 ]
	       }
	   }
	}
}